{
   "destination_addresses" : [
      "Charleston, SC, USA",
      "Greenville, SC, USA",
      "Memphis, TN, USA",
      "Nashville, TN, USA",
      "Knoxville, TN, USA",
      "Austin, TX, USA",
      "Beaumont, TX, USA",
      "Corpus Christi, TX, USA",
      "Dallas, TX, USA",
      "El Paso, TX, USA",
      "Houston, TX, USA",
      "San Antonio, TX, USA",
      "Salt Lake City, UT, USA",
      "Richmond, VA, USA",
      "Seattle, WA, USA",
      "Milwaukee, WI, USA"
   ],
   "origin_addresses" : [ "Dayton, OH, USA" ],
   "rows" : [
      {
         "elements" : [
            {
               "distance" : {
                  "text" : "1,068 km",
                  "value" : 1067858
               },
               "duration" : {
                  "text" : "10 hours 45 mins",
                  "value" : 38704
               },
               "status" : "OK"
            },
            {
               "distance" : {
                  "text" : "756 km",
                  "value" : 755630
               },
               "duration" : {
                  "text" : "8 hours 2 mins",
                  "value" : 28913
               },
               "status" : "OK"
            },
            {
               "distance" : {
                  "text" : "867 km",
                  "value" : 867385
               },
               "duration" : {
                  "text" : "8 hours 51 mins",
                  "value" : 31880
               },
               "status" : "OK"
            },
            {
               "distance" : {
                  "text" : "531 km",
                  "value" : 530887
               },
               "duration" : {
                  "text" : "5 hours 32 mins",
                  "value" : 19946
               },
               "status" : "OK"
            },
            {
               "distance" : {
                  "text" : "489 km",
                  "value" : 489011
               },
               "duration" : {
                  "text" : "5 hours 6 mins",
                  "value" : 18379
               },
               "status" : "OK"
            },
            {
               "distance" : {
                  "text" : "1,937 km",
                  "value" : 1936797
               },
               "duration" : {
                  "text" : "18 hours 16 mins",
                  "value" : 65778
               },
               "status" : "OK"
            },
            {
               "distance" : {
                  "text" : "1,771 km",
                  "value" : 1771231
               },
               "duration" : {
                  "text" : "16 hours 48 mins",
                  "value" : 60460
               },
               "status" : "OK"
            },
            {
               "distance" : {
                  "text" : "2,142 km",
                  "value" : 2141648
               },
               "duration" : {
                  "text" : "20 hours 33 mins",
                  "value" : 74007
               },
               "status" : "OK"
            },
            {
               "distance" : {
                  "text" : "1,624 km",
                  "value" : 1623808
               },
               "duration" : {
                  "text" : "15 hours 21 mins",
                  "value" : 55287
               },
               "status" : "OK"
            },
            {
               "distance" : {
                  "text" : "2,497 km",
                  "value" : 2497238
               },
               "duration" : {
                  "text" : "23 hours 17 mins",
                  "value" : 83802
               },
               "status" : "OK"
            },
            {
               "distance" : {
                  "text" : "1,809 km",
                  "value" : 1808674
               },
               "duration" : {
                  "text" : "17 hours 27 mins",
                  "value" : 62849
               },
               "status" : "OK"
            },
            {
               "distance" : {
                  "text" : "2,063 km",
                  "value" : 2063382
               },
               "duration" : {
                  "text" : "19 hours 29 mins",
                  "value" : 70133
               },
               "status" : "OK"
            },
            {
               "distance" : {
                  "text" : "2,660 km",
                  "value" : 2660094
               },
               "duration" : {
                  "text" : "1 day 1 hour",
                  "value" : 88516
               },
               "status" : "OK"
            },
            {
               "distance" : {
                  "text" : "819 km",
                  "value" : 818989
               },
               "duration" : {
                  "text" : "8 hours 22 mins",
                  "value" : 30138
               },
               "status" : "OK"
            },
            {
               "distance" : {
                  "text" : "3,805 km",
                  "value" : 3805308
               },
               "duration" : {
                  "text" : "1 day 11 hours",
                  "value" : 125711
               },
               "status" : "OK"
            },
            {
               "distance" : {
                  "text" : "634 km",
                  "value" : 634172
               },
               "duration" : {
                  "text" : "6 hours 32 mins",
                  "value" : 23507
               },
               "status" : "OK"
            }
         ]
      }
   ],
   "status" : "OK"
}
